LICENSE
MANIFEST.in
README.md
pyproject.toml
src/evalis/__init__.py
src/evalis/antlr4_adapter.py
src/evalis/ast.py
src/evalis/constants.py
src/evalis/error.py
src/evalis/eval.py
src/evalis/evalis.py
src/evalis/types.py
src/evalis/utils.py
src/evalis.egg-info/PKG-INFO
src/evalis.egg-info/SOURCES.txt
src/evalis.egg-info/dependency_links.txt
src/evalis.egg-info/requires.txt
src/evalis.egg-info/top_level.txt
src/evalis/__gen__/EvalisLexer.py
src/evalis/__gen__/EvalisListener.py
src/evalis/__gen__/EvalisParser.py
src/evalis/__gen__/EvalisVisitor.py
src/evalis/__gen__/grammar.py