Metadata-Version: 2.4
Name: evalis
Version: 0.2.1
Summary: A polyglot, safe, user-friendly expression evaluator.
Author-email: Paul Slaughter <paul@souldzin.com>
License-Expression: MIT
Project-URL: Homepage, https://github.com/GojiYoji/evalis
Project-URL: Repository, https://github.com/GojiYoji/evalis
Project-URL: Issues, https://github.com/GojiYoji/evalis/issues
Project-URL: Documentation, https://github.com/GojiYoji/evalis/tree/main/python
Keywords: expression,evaluator,parser,antlr,safe-eval
Classifier: Development Status :: 3 - Alpha
Classifier: Intended Audience :: Developers
Classifier: Programming Language :: Python :: 3
Classifier: Programming Language :: Python :: 3.10
Classifier: Programming Language :: Python :: 3.11
Classifier: Programming Language :: Python :: 3.12
Classifier: Programming Language :: Python :: 3.13
Classifier: Topic :: Software Development :: Libraries
Requires-Python: >=3.10
License-File: LICENSE
Requires-Dist: antlr4-python3-runtime==4.13.2
Provides-Extra: dev
Requires-Dist: antlr4-tools==0.2.2; extra == "dev"
Requires-Dist: black==25.1.0; extra == "dev"
Requires-Dist: build==1.3.0; extra == "dev"
Requires-Dist: flake8==7.2.0; extra == "dev"
Requires-Dist: pyright==1.1.400; extra == "dev"
Requires-Dist: pytest==8.4.1; extra == "dev"
Requires-Dist: pyyaml==6.0.2; extra == "dev"
Dynamic: license-file
